connection/__init__.py
connection/mysqlconnection.py
example_streamlit_mysql_connection_noah-0.0.2.dist-info/LICENSE.txt
example_streamlit_mysql_connection_noah-0.0.2.dist-info/METADATA
example_streamlit_mysql_connection_noah-0.0.2.dist-info/WHEEL
example_streamlit_mysql_connection_noah-0.0.2.dist-info/top_level.txt
example_streamlit_mysql_connection_noah-0.0.2.dist-info/RECORD
