Metadata-Version: 2.1
Name: example-streamlit-mysql-connection-noah
Version: 0.0.2
Summary: for test
Author: jeonghan
Author-email: junghwanshin@mz.co.kr
Classifier: Programming Language :: Python :: 3
Classifier: License :: OSI Approved :: MIT License
Classifier: Operating System :: OS Independent
Requires-Python: >=3.5
License-File: LICENSE.txt
